aiohttp_wrapper/__init__.py
aiohttp_wrapper/errors.py
aiohttp_wrapper/session_manager.py
aiohttp_wrapper-1.0.0.dist-info/DESCRIPTION.rst
aiohttp_wrapper-1.0.0.dist-info/METADATA
aiohttp_wrapper-1.0.0.dist-info/RECORD
aiohttp_wrapper-1.0.0.dist-info/WHEEL
aiohttp_wrapper-1.0.0.dist-info/metadata.json
aiohttp_wrapper-1.0.0.dist-info/top_level.txt
