Metadata-Version: 2.0
Name: aiohttp-wrapper
Version: 1.0.0
Summary: Abstraction of HTTP requests using aiohttp
Home-page: UNKNOWN
Author: MaT1g3R
Author-email: UNKNOWN
License: MIT
Platform: UNKNOWN
Classifier: Development Status :: 5 - Production/Stable
Classifier: Intended Audience :: Developers
Classifier: Natural Language :: English
Classifier: License :: OSI Approved :: MIT License
Classifier: Programming Language :: Python
Classifier: Programming Language :: Python :: 3.5
Classifier: Programming Language :: Python :: 3.6
Requires-Dist: aiohttp (>=2.2.5)
Requires-Dist: xmltodict (>=0.11.0)
